Metadata-Version: 2.1
Name: kage-genotyper
Version: 2.0.6
Summary: KAGE
Home-page: http://github.com/ivargr/kage
Author: Ivar Grytten
Author-email: 
License: MIT
Classifier: Programming Language :: Python :: 3
License-File: LICENSE
